txaio/__init__.py
txaio/_common.py
txaio/_iotype.py
txaio/_unframework.py
txaio/_util.py
txaio/_version.py
txaio/aio.py
txaio/interfaces.py
txaio/testutil.py
txaio/tx.py
txaio/with_asyncio.py
txaio/with_twisted.py
txaio-22.2.1.dist-info/LICENSE
txaio-22.2.1.dist-info/METADATA
txaio-22.2.1.dist-info/WHEEL
txaio-22.2.1.dist-info/top_level.txt
txaio-22.2.1.dist-info/zip-safe
txaio-22.2.1.dist-info/RECORD
