Metadata-Version: 2.1
Name: txaio
Version: 22.2.1
Summary: Compatibility API between asyncio/Twisted/Trollius
Home-page: https://github.com/crossbario/txaio
Author: Crossbar.io Technologies GmbH
Author-email: autobahnws@googlegroups.com
License: MIT License
Keywords: asyncio twisted trollius coroutine
Platform: Any
Classifier: License :: OSI Approved :: MIT License
Classifier: Development Status :: 5 - Production/Stable
Classifier: Environment :: Console
Classifier: Framework :: Twisted
Classifier: Intended Audience :: Developers
Classifier: Operating System :: OS Independent
Classifier: Programming Language :: Python
Classifier: Programming Language :: Python :: 3
Classifier: Programming Language :: Python :: 3.6
Classifier: Programming Language :: Python :: 3.7
Classifier: Programming Language :: Python :: 3.8
Classifier: Programming Language :: Python :: 3.9
Classifier: Programming Language :: Python :: Implementation :: CPython
Classifier: Programming Language :: Python :: Implementation :: PyPy
Classifier: Topic :: Software Development :: Libraries
Classifier: Topic :: Software Development :: Libraries :: Application Frameworks
Requires-Python: >=3.6
Provides-Extra: twisted
Provides-Extra: asyncio
Provides-Extra: dev
Provides-Extra: all
